height_parser/.DS_Store
height_parser/__init__.py
height_parser/parser.py
height_parser-0.1.5.dist-info/LICENSE
height_parser-0.1.5.dist-info/METADATA
height_parser-0.1.5.dist-info/WHEEL
height_parser-0.1.5.dist-info/RECORD
