Metadata-Version: 2.3
Name: height-parser
Version: 0.1.5
Summary: Convert date-like strings (e.g., 6/11/2000) into heights
License: MIT
Author: Ananya Srinivas 25763727
Author-email: anniesrinivas66@gmail.com
Requires-Python: >=3.11
Classifier: License :: OSI Approved :: MIT License
Classifier: Programming Language :: Python :: 3
Classifier: Programming Language :: Python :: 3.11
Classifier: Programming Language :: Python :: 3.12
Classifier: Programming Language :: Python :: 3.13
